cbs_mapf/__init__.py
cbs_mapf/agent.py
cbs_mapf/assigner.py
cbs_mapf/constraint_tree.py
cbs_mapf/constraints.py
cbs_mapf/planner.py
cbs_mapf-0.5.dist-info/LICENSE.txt 
cbs_mapf-0.5.dist-info/METADATA
cbs_mapf-0.5.dist-info/WHEEL
cbs_mapf-0.5.dist-info/top_level.txt
cbs_mapf-0.5.dist-info/RECORD
