Metadata-Version: 2.1
Name: cbs-mapf
Version: 0.5
Summary: Anonymous Multi-Agent Path Finding with Conflict-Based Search and Space-Time A*
Home-page: https://github.com/GavinPHR/Multi-Agent-Path-Finding
Author: Haoran Peng
Author-email: gavinsweden@gmail.com
License: MIT
Keywords: multi-agent-path-finding,anonymous-agent,conflict-based-search,mapf,cbs,a-star
Platform: UNKNOWN
Classifier: Development Status :: 4 - Beta
Classifier: Intended Audience :: Developers
Classifier: Topic :: Software Development :: Build Tools
Classifier: License :: OSI Approved :: MIT License
Requires-Python: >=3.5
Requires-Dist: numpy
Requires-Dist: scipy
Requires-Dist: space-time-astar
